sitech_notifier/__init__.py
sitech_notifier/admin.py
sitech_notifier/apps.py
sitech_notifier/core.py
sitech_notifier/delivery/__init__.py
sitech_notifier/delivery/backends.py
sitech_notifier/events.py
sitech_notifier/exceptions.py
sitech_notifier/migrations/0001_initial.py
sitech_notifier/migrations/0002_auto_20191205_1424.py
sitech_notifier/migrations/0003_auto_20191212_1519.py
sitech_notifier/migrations/__init__.py
sitech_notifier/models.py
sitech_notifier/notifications.py
sitech_notifier/settings.py
sitech_notifier/tasks.py
sitech_notifier/templates/sitech_notifier/pusher-notifications.html
sitech_notifier/templatetags/__init__.py
sitech_notifier/templatetags/sitech_notifier.py
sitech_notifier/urls.py
sitech_notifier/utils.py
sitech_notifier/views.py
sitech_notifier-2.0.7.dist-info/LICENSE
sitech_notifier-2.0.7.dist-info/WHEEL
sitech_notifier-2.0.7.dist-info/METADATA
sitech_notifier-2.0.7.dist-info/RECORD
