Metadata-Version: 2.1
Name: sitech-notifier
Version: 2.0.7
Summary: Notification library for real-time, sms and email notifications
Author: Norbert Cyran
Author-email: norbert@ulam.io
Requires-Python: >=3.6,<4.0
Classifier: Environment :: Web Environment
Classifier: Framework :: Django
Classifier: Operating System :: OS Independent
Classifier: Programming Language :: Python :: 3
Classifier: Programming Language :: Python :: 3.6
Classifier: Programming Language :: Python :: 3.7
Classifier: Programming Language :: Python :: 3.8
Provides-Extra: realtime
Requires-Dist: celery (>=4.3,<5.0)
Requires-Dist: django (>=2.0,<4.0)
Requires-Dist: django-render-block (>=0.6.0,<0.7.0)
Requires-Dist: pusher (>=2.0,<3.0); extra == "realtime"
